pyvalence/__init__.py
pyvalence/analyze/__init__.py
pyvalence/analyze/gcquant.py
pyvalence/analyze/peaks.py
pyvalence/build/__init__.py
pyvalence/build/agilentgcms.py
pyvalence-0.0.1.3.dist-info/LICENSE
pyvalence-0.0.1.3.dist-info/METADATA
pyvalence-0.0.1.3.dist-info/WHEEL
pyvalence-0.0.1.3.dist-info/top_level.txt
pyvalence-0.0.1.3.dist-info/RECORD
