Metadata-Version: 2.1
Name: pyvalence
Version: 0.0.1.3
Summary: Package for processing analytical chemistry data.
Home-page: https://audere.github.com/valence
Author: Audere Labs
Author-email: audere.labs@gmail.com
Maintainer-email: 
License: BSD
Platform: Any
Classifier: Development Status :: 1 - Planning
Classifier: Environment :: Console
Classifier: Intended Audience :: Science/Research
Classifier: Operating System :: OS Independent
Classifier: Programming Language :: Python :: 3.3
Classifier: Programming Language :: Python :: 3.4
Classifier: Programming Language :: Python :: 3.5
Classifier: Programming Language :: Python :: 3.6
Classifier: Topic :: Scientific/Engineering :: Chemistry
Requires-Dist: numpy
Requires-Dist: scipy
Requires-Dist: pandas
